STP_LB-0.1.dev0.data/scripts/stserver
STP_LB-0.1.dev0.dist-info/DESCRIPTION.rst
STP_LB-0.1.dev0.dist-info/METADATA
STP_LB-0.1.dev0.dist-info/RECORD
STP_LB-0.1.dev0.dist-info/WHEEL
STP_LB-0.1.dev0.dist-info/metadata.json
STP_LB-0.1.dev0.dist-info/top_level.txt
stp/__init__.py
stp/app.py
stp/banner.py
stp/conf/logging.conf
stp/conf/sts.yaml
stp/core/__init__.py
stp/core/master.py
stp/core/server_info.py
stp/core/server_msg.py
stp/core/slaver.py
stp/core/sts_manager.py
stp/core/task.py
stp/storage/__init__.py
stp/storage/storage.py
stp/tasks/__init__.py
stp/tasks/task.py
stp/tasks/processor/__init__.py
stp/tasks/processor/fp_processor/__init__.py
stp/tasks/processor/fp_processor/processor.py
stp/tasks/processor/hello_processor/__init__.py
stp/tasks/processor/hello_processor/processor.py
stp/tasks/processor/test_processor/__init__.py
stp/tasks/processor/test_processor/processor.py
stp/thrift/__init__.py
stp/thrift/client.py
stp/thrift/server.py
stp/thrift/gen-py/__init__.py
stp/thrift/gen-py/server_communicate/ServerCommunicate.py
stp/thrift/gen-py/server_communicate/__init__.py
stp/thrift/gen-py/server_communicate/constants.py
stp/thrift/gen-py/server_communicate/ttypes.py
stp/utils/__init__.py
stp/utils/daemonize.py
stp/utils/ip_util.py
stp/utils/multicast.py
stp/utils/server_communicate_util.py
stp/utils/server_info.py
stp/web/__init__.py
stp/web/api.py
